{
    "title": "Chrono Trigger",
    "author": "Square Enix.",
    "categories": [
        "game"
    ],
    "systems": [
        "DS"
    ],
    "downloads": {
		"Chrono Trigger (Europe) (En,Fr).nds": {
			"url": "https://archive.org/download/NintendoDSRomCollectionByGhostware/Chrono%20Trigger%20%28Europe%29%20%28En%2CFr%29.nds"
		}
	},
    "screenshots": [{
        "url": "https://raw.githubusercontent.com/TheRinzler65/NDS-Shop/main/docs/assets/images/screenshots/chronotrigger/chronotrigger.png",
        "description": "Game preview"
        },{
        "url": "https://raw.githubusercontent.com/TheRinzler65/NDS-Shop/main/docs/assets/images/boxart/Chrono%20Trigger%20(Europe)%20(En%2CFr).nds.png",
        "description": "Boxart"
    }],
    "icon": "https://raw.githubusercontent.com/TheRinzler65/NDS-Shop/main/docs/assets/images/icons/chronotrigger.png",
    "version": "(Europe) (En,Fr)",
    "created": "2024-08-10T19:42:58+02:00",
    "scripts": {
        "Chrono Trigger (Europe) (En,Fr).nds": [
            {
                "type": "downloadFile",
                "file": "https://raw.githubusercontent.com/TheRinzler65/NDS-Shop/main/docs/assets/images/boxart/Chrono%20Trigger%20(Europe)%20(En%2CFr).nds.png",
                "output": "/_nds/TwiLightMenu/boxart/Chrono Trigger (Europe) (En,Fr).nds.png"
            },
            {
                "type": "downloadFile",
                "file": "https://archive.org/download/NintendoDSRomCollectionByGhostware/Chrono%20Trigger%20%28Europe%29%20%28En%2CFr%29.nds",
                "output": "/roms/nds/Chrono Trigger (Europe) (En,Fr).nds"
            }
        ]
    }
}