{
    "title": "Code Lyoko: Fall of X.A.N.A.",
    "author": "The Game Factory",
    "categories": [
        "game"
    ],
    "systems": [
        "DS"
    ],
    "screenshots": [{
        "url": "",
        "description": ""
        },{
        "url": "",
        "description": ""
    }],
    "icon": "",
    "version": "",
    "created": "",
    "scripts": {
        "": [
            {
                "type": "downloadFile",
                "file": "",
                "output": "/_nds/TwiLightMenu/boxart/"
            },
            {
                "type": "downloadFile",
                "file": "",
                "output": "/roms/nds/"
            }
        ]
    }
} 